{
  "db_name": "SQLite",
  "query": "\n            INSERT INTO reviews (repo_name, pr_number, reviewer, state, submitted_at, updated_at)\n            VALUES (?, ?, ?, ?, CURRENT_TIMESTAMP, CURRENT_TIMESTAMP)\n            ON CONFLICT(repo_name, pr_number, reviewer) DO UPDATE SET\n                state = EXCLUDED.state,\n                updated_at = CURRENT_TIMESTAMP\n            ",
  "describe": {
    "columns": [],
    "parameters": {
      "Right": 4
    },
    "nullable": []
  },
  "hash": "3861e519cf11e09ae3520ffdabe76a956a0ae5a47aae03823383f85e473bb5a8"
}
